mypkg7727/__init__.py
mypkg7727/mypkg7727.py
mypkg7727-0.1.0.dist-info/LICENSE
mypkg7727-0.1.0.dist-info/WHEEL
mypkg7727-0.1.0.dist-info/METADATA
mypkg7727-0.1.0.dist-info/RECORD
